etao/__init__.py
etao/analysis.py
etao/bitwise.py
etao/ciphers.py
etao/codecs.py
etao/freq.py
etao/pen.py
etao/scorers.py
etao/util.py
etao-1.0.1.dist-info/LICENSE
etao-1.0.1.dist-info/METADATA
etao-1.0.1.dist-info/WHEEL
etao-1.0.1.dist-info/top_level.txt
etao-1.0.1.dist-info/zip-safe
etao-1.0.1.dist-info/RECORD
