Metadata-Version: 2.1
Name: etao
Version: 1.0.1
Summary: Simple cryptanalysis library
Home-page: https://github.com/jamchamb/etao
Author: James Chambers
Author-email: jameschambers2@gmail.com
License: GPLv3
Keywords: cryptography,cryptanalysis,ciphers
Platform: UNKNOWN
